chemfst-0.2.0.dist-info/METADATA
chemfst-0.2.0.dist-info/WHEEL
chemfst-0.2.0.dist-info/licenses/LICENSE
chemfst/__init__.py
chemfst/chemfst.pyd
chemfst-0.2.0.dist-info/RECORD
