Metadata-Version: 2.4
Name: chemfst
Version: 0.2.0
Classifier: Programming Language :: Python :: 3
Classifier: Programming Language :: Python :: 3.11
Classifier: Programming Language :: Python :: 3.12
Classifier: Programming Language :: Python :: 3.13
Classifier: Programming Language :: Rust
Classifier: Topic :: Scientific/Engineering :: Chemistry
Classifier: Topic :: Software Development :: Libraries
Classifier: Topic :: Text Processing :: Indexing
License-File: LICENSE
Summary: Python bindings for ChemFST - a high-performance chemical name search library
Author: Emanuel Ehmki
Requires-Python: >=3.11
Project-URL: Homepage, https://github.com/esrehmki/ChemFST
Project-URL: Documentation, https://github.com/esrehmki/ChemFST
Project-URL: Repository, https://github.com/esrehmki/ChemFST
